{
    "records": [
        {
            "attributes": {
                "type": "Account",
                "referenceId": "AccountRef1"
            },
            "Name": "Genepoint",
            "Phone": "9897898978",
            "BillingCountry": "India",
            "Industry": "Agriculture",
            "Type": "Prospect",
            "Website": "www.genepoint.com"
        },
        {
            "attributes": {
                "type": "Account",
                "referenceId": "AccountRef2"
            },
            "Name": "TCS",
            "Phone": "9897898178",
            "BillingCountry": "India",
            "Industry": "Agriculture",
            "Type": "Prospect",
            "Website": "www.genepoint.com"
        },
        {
            "attributes": {
                "type": "Account",
                "referenceId": "AccountRef3"
            },
            "Name": "Accenture",
            "Phone": "9897838978",
            "BillingCountry": "India",
            "Industry": "Agriculture",
            "Type": "Prospect",
            "Website": "www.genepoint.com"
        },
        {
            "attributes": {
                "type": "Account",
                "referenceId": "AccountRef4"
            },
            "Name": "KPMG",
            "Phone": "9897898178",
            "BillingCountry": "India",
            "Industry": "Agriculture",
            "Type": "Prospect",
            "Website": "www.genepoint.com"
        },
        {
            "attributes": {
                "type": "Account",
                "referenceId": "AccountRef5"
            },
            "Name": "Capgemini",
            "Phone": "9897898975",
            "BillingCountry": "India",
            "Industry": "Agriculture",
            "Type": "Prospect",
            "Website": "www.genepoint.com"
        },
        {
            "attributes": {
                "type": "Account",
                "referenceId": "AccountRef6"
            },
            "Name": "Amazon",
            "Phone": "9897898979",
            "BillingCountry": "India",
            "Industry": "Agriculture",
            "Type": "Prospect",
            "Website": "www.genepoint.com"
        }
    ]
}